MANIFEST.in
README.md
setup.py
weimobUI/__init__.py
weimobUI/__main__.py
weimobUI/initialization.py
weimobUI/TestFrame/__init__.py
weimobUI/TestFrame/core.py
weimobUI/TestFrame/process.py
weimobUI/actions/__init__.py
weimobUI/actions/browser.py
weimobUI/common/__init__.py
weimobUI/common/glo_var_controller.py
weimobUI/common/xlxs_handle.py
weimobUI/projectFolder/__init__.py
weimobUI/projectFolder/conf_folder.py
weimobUI/projectFolder/main_folder.py
weimobUI/projectFolder/report_folder.py
weimobUI/projectFolder/settings.py
weimobUI/projectFolder/template.xlsx
weimobUI/projectFolder/testcases_folder.py
weimob_ui.egg-info/PKG-INFO
weimob_ui.egg-info/SOURCES.txt
weimob_ui.egg-info/dependency_links.txt
weimob_ui.egg-info/entry_points.txt
weimob_ui.egg-info/not-zip-safe
weimob_ui.egg-info/requires.txt
weimob_ui.egg-info/top_level.txt