Metadata-Version: 2.1
Name: weimob-ui
Version: 0.3.1
Summary: ui自动化框架
Home-page: UNKNOWN
Author: jianwei.lv
Author-email: jianwei.lv@weimob.com
License: UNKNOWN
Platform: UNKNOWN
Requires-Python: >=3.6
